variablz-pyqt/Table.py
variablz-pyqt/__init__.py
variablz_pyqt/Table.py
variablz_pyqt/__init__.py
variablz_qt/Table.py
variablz_qt/__init__.py
variablz_qt-0.0.2.dist-info/METADATA
variablz_qt-0.0.2.dist-info/WHEEL
variablz_qt-0.0.2.dist-info/top_level.txt
variablz_qt-0.0.2.dist-info/RECORD
